ezlmm/__init__.py
ezlmm/core.py
ezlmm-0.4.2.dist-info/METADATA
ezlmm-0.4.2.dist-info/WHEEL
ezlmm-0.4.2.dist-info/top_level.txt
ezlmm-0.4.2.dist-info/RECORD
