Metadata-Version: 2.1
Name: ezlmm
Version: 0.4.2
Summary: Python interface of Linear Mixed Model analysis in R language
Home-page: https://github.com/Paradeluxe/ezLMM
Author: Paradeluxe
Author-email: paradeluxe3726@gmail.com
License: MIT
Keywords: Linear Mixed Model
Requires-Dist: numpy >=1.26.4
Requires-Dist: pandas >=2.2.2
Requires-Dist: rpy2 >=3.5.16
